LICENSE
MANIFEST.in
README.rst
setup.py
shelvedump.py
shelvedump.egg-info/PKG-INFO
shelvedump.egg-info/SOURCES.txt
shelvedump.egg-info/dependency_links.txt
shelvedump.egg-info/entry_points.txt
shelvedump.egg-info/requires.txt
shelvedump.egg-info/top_level.txt