Metadata-Version: 1.1
Name: shelvedump
Version: 1.0
Summary: dump the content of a Python shelve database to JSON
Home-page: https://github.com/miracle2k/shelvedump
Author: Michael Elsdörfer
Author-email: michael@elsdoerfer.com
License: BSD
Platform: UNKNOWN
Classifier: Development Status :: 5 - Production/Stable
Classifier: Intended Audience :: Developers
Classifier: License :: OSI Approved :: BSD License
Classifier: Operating System :: OS Independent
Classifier: Programming Language :: Python
Classifier: Programming Language :: Python :: 3
